{"location": {"zip_code": "11215", "address3": "", "city": "Brooklyn", "address2": null, "state": "NY", "address1": null, "country": "US"}, "is_closed": false, "photos": ["https://s3-media4.fl.yelpcdn.com/bphoto/MadXQZtycOZU3l7Vy8zpvQ/o.jpg", "https://s3-media4.fl.yelpcdn.com/bphoto/IJaP3nFt1dva0vNPMg6B4g/o.jpg"], "url": "https://www.yelp.com/biz/gemma-deller-brooklyn-3?adjust_creative=92p07_JjKyriZTQxAXRiKQ&utm_campaign=yelp_api_v3&utm_medium=api_v3_business_lookup&utm_source=92p07_JjKyriZTQxAXRiKQ", "review_count": 19, "image_url": "https://s3-media2.fl.yelpcdn.com/bphoto/MadXQZtycOZU3l7Vy8zpvQ/o.jpg", "term": "attractions", "id": "gemma-deller-brooklyn-3", "phone": "+13477092121", "rating": 4.0, "categories": [{"alias": "psychic_astrology", "title": "Psychics & Astrologers"}], "coordinates": {"longitude": -73.9800645, "latitude": 40.6681669}, "name": "Gemma Deller", "is_claimed": true}