{"location": {"zip_code": "11101", "address3": "", "city": "Long Island City", "state": "NY", "address2": "", "address1": "12-09 Jackson Ave", "country": "US"}, "image_url": "https://s3-media1.fl.yelpcdn.com/bphoto/smIYyfVGImzgUiUrd-v64Q/o.jpg", "is_closed": false, "photos": ["https://s3-media2.fl.yelpcdn.com/bphoto/smIYyfVGImzgUiUrd-v64Q/o.jpg", "https://s3-media3.fl.yelpcdn.com/bphoto/3qYmU108pZ-EzjcvZ3E-AA/o.jpg", "https://s3-media4.fl.yelpcdn.com/bphoto/Cly_dSp6o6iWzpUAoi0uDQ/o.jpg"], "url": "https://www.yelp.com/biz/mu-ramen-long-island-city-2?adjust_creative=92p07_JjKyriZTQxAXRiKQ&utm_campaign=yelp_api_v3&utm_medium=api_v3_business_lookup&utm_source=92p07_JjKyriZTQxAXRiKQ", "review_count": 672, "hours": [{"hours_type": "REGULAR", "is_open_now": false, "open": [{"start": "1700", "is_overnight": false, "end": "2200", "day": 0}, {"start": "1700", "is_overnight": false, "end": "2200", "day": 1}, {"start": "1700", "is_overnight": false, "end": "2200", "day": 2}, {"start": "1700", "is_overnight": false, "end": "2200", "day": 3}, {"start": "1700", "is_overnight": false, "end": "2300", "day": 4}, {"start": "1700", "is_overnight": false, "end": "2300", "day": 5}, {"start": "1700", "is_overnight": false, "end": "2200", "day": 6}]}], "term": "restaurants", "price": "$$", "id": "mu-ramen-long-island-city-2", "phone": "+19178688903", "rating": 4.0, "categories": [{"alias": "ramen", "title": "Ramen"}], "coordinates": {"longitude": -73.950631, "latitude": 40.743797}, "name": "Mu Ramen", "is_claimed": true}