{"location": {"zip_code": "G41 3YR", "address3": "", "city": "Glasgow", "address2": "", "state": "GLG", "address1": "67 Kilmarnock Road", "country": "GB"}, "image_url": "https://s3-media1.fl.yelpcdn.com/bphoto/7EKyb-DlrcAZiHBv798Qhg/o.jpg", "is_closed": false, "photos": ["https://s3-media3.fl.yelpcdn.com/bphoto/7EKyb-DlrcAZiHBv798Qhg/o.jpg", "https://s3-media1.fl.yelpcdn.com/bphoto/4dnKpWHJX5wMdI5ugfNu4w/o.jpg", "https://s3-media1.fl.yelpcdn.com/bphoto/e7Dvq7MhgdUDwPe5fC9hmg/o.jpg"], "url": "https://www.yelp.com/biz/black-dove-glasgow?adjust_creative=92p07_JjKyriZTQxAXRiKQ&utm_campaign=yelp_api_v3&utm_medium=api_v3_business_lookup&utm_source=92p07_JjKyriZTQxAXRiKQ", "review_count": 11, "hours": [{"hours_type": "REGULAR", "is_open_now": false, "open": [{"day": 0, "is_overnight": false, "start": "1000", "end": "2200"}, {"day": 1, "is_overnight": false, "start": "1000", "end": "2200"}, {"day": 2, "is_overnight": false, "start": "1000", "end": "2200"}, {"day": 3, "is_overnight": false, "start": "1000", "end": "2200"}, {"day": 4, "is_overnight": false, "start": "1000", "end": "2200"}, {"day": 5, "is_overnight": false, "start": "0800", "end": "2300"}, {"day": 6, "is_overnight": false, "start": "1000", "end": "2100"}]}], "term": "restaurants", "price": "\u00a3\u00a3\u00a3", "id": "black-dove-glasgow", "phone": "+441412311021", "rating": 4.0, "categories": [{"title": "Cocktail Bars", "alias": "cocktailbars"}, {"title": "Italian", "alias": "italian"}], "coordinates": {"longitude": -4.2831407, "latitude": 55.8285332}, "name": "Black Dove", "is_claimed": false}