{"location": {"zip_code": "1041", "address3": "", "city": "Auckland", "address2": "Mount Roskill", "state": "AUK", "address1": "77 Gifford Ave", "country": "NZ"}, "is_closed": false, "photos": ["https://s3-media1.fl.yelpcdn.com/bphoto/3Hi7teHe0LcSMWzbm22EEw/o.jpg", "https://s3-media1.fl.yelpcdn.com/bphoto/y2FZLrTgvBHY96b_pYLiXw/o.jpg", "https://s3-media3.fl.yelpcdn.com/bphoto/lxi2tsmv_EHry-Iwd1HS_Q/o.jpg"], "image_url": "https://s3-media2.fl.yelpcdn.com/bphoto/3Hi7teHe0LcSMWzbm22EEw/o.jpg", "review_count": 0, "url": "https://www.yelp.com/biz/ikhlas-tours-auckland?adjust_creative=92p07_JjKyriZTQxAXRiKQ&utm_campaign=yelp_api_v3&utm_medium=api_v3_business_lookup&utm_source=92p07_JjKyriZTQxAXRiKQ", "term": "hotels", "id": "ikhlas-tours-auckland", "phone": "+64212091079", "rating": 0.0, "categories": [{"title": "Tours", "alias": "tours"}, {"title": "RV Rental", "alias": "rvrental"}, {"title": "Car Rental", "alias": "carrental"}], "coordinates": {"longitude": 174.73848, "latitude": -36.90385}, "hours": [{"hours_type": "REGULAR", "is_open_now": true, "open": [{"end": "0000", "is_overnight": false, "start": "0000", "day": 0}, {"end": "0000", "is_overnight": false, "start": "0000", "day": 1}, {"end": "0000", "is_overnight": false, "start": "0000", "day": 2}, {"end": "0000", "is_overnight": false, "start": "0000", "day": 3}, {"end": "0000", "is_overnight": false, "start": "0000", "day": 4}, {"end": "0000", "is_overnight": false, "start": "0000", "day": 5}, {"end": "0000", "is_overnight": false, "start": "0000", "day": 6}]}], "name": "Ikhlas Tours", "is_claimed": true}