{"location": {"zip_code": "", "address3": "", "city": "Auckland", "address2": "Wynyard Quarter", "state": "AUK", "address1": "Cnr Beaumont & Jellicoe St", "country": "NZ"}, "is_closed": false, "photos": [], "url": "https://www.yelp.com/biz/silo-park-auckland-2?adjust_creative=92p07_JjKyriZTQxAXRiKQ&utm_campaign=yelp_api_v3&utm_medium=api_v3_business_lookup&utm_source=92p07_JjKyriZTQxAXRiKQ", "review_count": 1, "image_url": "", "term": "attractions", "id": "silo-park-auckland-2", "phone": "+4493368820", "rating": 5.0, "categories": [{"alias": "parks", "title": "Parks"}], "coordinates": {"longitude": 174.7549286, "latitude": -36.8403702}, "name": "Silo Park", "is_claimed": false}