{"location": {"zip_code": "75018", "address3": null, "city": "Paris", "address2": null, "state": "75", "address1": "10 place Charles Dullin", "country": "FR"}, "is_closed": false, "photos": ["https://s3-media2.fl.yelpcdn.com/bphoto/SraODOMfIFZzM1jRdqHt0w/o.jpg", "https://s3-media2.fl.yelpcdn.com/bphoto/AaWnESHWgS8WLJ0cK4H7pQ/o.jpg", "https://s3-media2.fl.yelpcdn.com/bphoto/23tReK1iK1ljfRNypVrbkw/o.jpg"], "url": "https://www.yelp.com/biz/adagio-city-aparthotel-paris-2?adjust_creative=92p07_JjKyriZTQxAXRiKQ&utm_campaign=yelp_api_v3&utm_medium=api_v3_business_lookup&utm_source=92p07_JjKyriZTQxAXRiKQ", "review_count": 3, "price": "\u20ac\u20ac", "term": "attractions", "coordinates": {"longitude": 2.342556, "latitude": 48.88335}, "id": "adagio-city-aparthotel-paris-2", "phone": "+33142571455", "rating": 3.5, "categories": [{"alias": "hotels", "title": "Hotels"}], "image_url": "https://s3-media1.fl.yelpcdn.com/bphoto/SraODOMfIFZzM1jRdqHt0w/o.jpg", "name": "Adagio City Aparthotel", "is_claimed": false}