{"location": {"zip_code": "60613", "address3": "", "city": "Chicago", "state": "IL", "address2": "", "address1": "838 W Montrose Ave", "country": "US"}, "image_url": "https://s3-media1.fl.yelpcdn.com/bphoto/s89GCL0yHvsSen-t166y8w/o.jpg", "is_closed": false, "photos": ["https://s3-media4.fl.yelpcdn.com/bphoto/s89GCL0yHvsSen-t166y8w/o.jpg", "https://s3-media1.fl.yelpcdn.com/bphoto/IUj9o8tQRdXusTEHgZV9mg/o.jpg", "https://s3-media3.fl.yelpcdn.com/bphoto/OURRT4Ns8VMehkvpQqS07g/o.jpg"], "url": "https://www.yelp.com/biz/loving-heart-chicago?adjust_creative=92p07_JjKyriZTQxAXRiKQ&utm_campaign=yelp_api_v3&utm_medium=api_v3_business_lookup&utm_source=92p07_JjKyriZTQxAXRiKQ", "review_count": 123, "hours": [{"hours_type": "REGULAR", "is_open_now": false, "open": [{"start": "1100", "is_overnight": false, "end": "2000", "day": 0}, {"start": "1100", "is_overnight": false, "end": "2000", "day": 1}, {"start": "1100", "is_overnight": false, "end": "2000", "day": 2}, {"start": "1100", "is_overnight": false, "end": "2000", "day": 3}, {"start": "1100", "is_overnight": false, "end": "2000", "day": 4}, {"start": "1100", "is_overnight": false, "end": "2000", "day": 5}]}], "term": "restaurants", "price": "$", "id": "loving-heart-chicago", "phone": "+17735615399", "rating": 5.0, "categories": [{"alias": "vegan", "title": "Vegan"}, {"alias": "vegetarian", "title": "Vegetarian"}, {"alias": "cafes", "title": "Cafes"}], "coordinates": {"longitude": -87.6515285, "latitude": 41.9619233}, "name": "Loving Heart", "is_claimed": true}