{"location": {"zip_code": "02116", "address3": "", "city": "Boston", "state": "MA", "address2": "", "address1": "74 Warrenton St", "country": "US"}, "image_url": "https://s3-media1.fl.yelpcdn.com/bphoto/pZh6dSiA8cWqn1BM518Tqg/o.jpg", "is_closed": false, "photos": ["https://s3-media2.fl.yelpcdn.com/bphoto/pZh6dSiA8cWqn1BM518Tqg/o.jpg", "https://s3-media1.fl.yelpcdn.com/bphoto/YbKKfcD1Zn0c-eypImQwuQ/o.jpg", "https://s3-media1.fl.yelpcdn.com/bphoto/Lxxp5FHh1ih-tAR51s4TiA/o.jpg"], "hours": [{"hours_type": "REGULAR", "is_open_now": true, "open": [{"start": "1200", "is_overnight": false, "end": "1800", "day": 0}, {"start": "1200", "is_overnight": false, "end": "1800", "day": 1}, {"start": "1200", "is_overnight": false, "end": "2030", "day": 2}, {"start": "1200", "is_overnight": false, "end": "2030", "day": 3}, {"start": "1200", "is_overnight": false, "end": "2030", "day": 4}, {"start": "1000", "is_overnight": false, "end": "2230", "day": 5}, {"start": "1200", "is_overnight": false, "end": "1730", "day": 6}]}], "review_count": 64, "url": "https://www.yelp.com/biz/charles-playhouse-boston?adjust_creative=92p07_JjKyriZTQxAXRiKQ&utm_campaign=yelp_api_v3&utm_medium=api_v3_business_lookup&utm_source=92p07_JjKyriZTQxAXRiKQ", "term": "attractions", "id": "charles-playhouse-boston", "phone": "+16174266912", "rating": 4.0, "categories": [{"alias": "theater", "title": "Performing Arts"}], "coordinates": {"longitude": -71.06618, "latitude": 42.34999}, "name": "Charles Playhouse", "is_claimed": true}