{"location": {"zip_code": "02453", "address3": "", "city": "Waltham", "address2": "", "state": "MA", "address1": "Moody St", "country": "US"}, "is_closed": false, "photos": ["https://s3-media1.fl.yelpcdn.com/bphoto/kCdvfJOcIzDT0n7tjiPH2g/o.jpg", "https://s3-media1.fl.yelpcdn.com/bphoto/e_9iJVYkg17sWupy6CgTXA/o.jpg"], "image_url": "https://s3-media3.fl.yelpcdn.com/bphoto/kCdvfJOcIzDT0n7tjiPH2g/o.jpg", "review_count": 1, "url": "https://www.yelp.com/biz/moody-street-bridge-waltham-2?adjust_creative=92p07_JjKyriZTQxAXRiKQ&utm_campaign=yelp_api_v3&utm_medium=api_v3_business_lookup&utm_source=92p07_JjKyriZTQxAXRiKQ", "term": "attractions", "id": "moody-street-bridge-waltham-2", "phone": "", "rating": 4.0, "categories": [{"title": "Landmarks & Historical Buildings", "alias": "landmarks"}], "coordinates": {"longitude": -71.2365495041013, "latitude": 42.3732315433583}, "name": "Moody Street Bridge", "is_claimed": false}