{"location": {"zip_code": "02111", "address3": "", "city": "Boston", "address2": "", "state": "MA", "address1": "640 Atlantic Ave", "country": "US"}, "image_url": "https://s3-media3.fl.yelpcdn.com/bphoto/ttIq8OrIrBMKyC4isvh4WA/o.jpg", "is_closed": false, "photos": ["https://s3-media3.fl.yelpcdn.com/bphoto/ttIq8OrIrBMKyC4isvh4WA/o.jpg", "https://s3-media4.fl.yelpcdn.com/bphoto/TXegdPuZNbvb8PyDjoQhlQ/o.jpg", "https://s3-media4.fl.yelpcdn.com/bphoto/wJoljOaaiviE65Y1lVosUA/o.jpg"], "url": "https://www.yelp.com/biz/tavern-in-the-square-boston-3?adjust_creative=92p07_JjKyriZTQxAXRiKQ&utm_campaign=yelp_api_v3&utm_medium=api_v3_business_lookup&utm_source=92p07_JjKyriZTQxAXRiKQ", "review_count": 33, "hours": [{"hours_type": "REGULAR", "is_open_now": true, "open": [{"start": "1000", "is_overnight": false, "end": "2300", "day": 0}, {"start": "1000", "is_overnight": false, "end": "2300", "day": 1}, {"start": "1000", "is_overnight": false, "end": "2300", "day": 2}, {"start": "1000", "is_overnight": false, "end": "2300", "day": 3}, {"start": "1000", "is_overnight": false, "end": "2300", "day": 4}, {"start": "1000", "is_overnight": false, "end": "2300", "day": 5}, {"start": "1000", "is_overnight": false, "end": "2300", "day": 6}]}], "term": "restaurants", "price": "$$", "id": "tavern-in-the-square-boston-3", "phone": "+18572334717", "rating": 4.0, "categories": [{"title": "American (New)", "alias": "newamerican"}, {"title": "Sports Bars", "alias": "sportsbars"}], "coordinates": {"longitude": -71.055495, "latitude": 42.352518}, "name": "Tavern In the Square", "is_claimed": true}