{"location": {"zip_code": "BL6 7SB", "address3": "", "city": "Preston", "address2": "", "state": "LAN", "address1": null, "country": "GB"}, "is_closed": false, "photos": ["https://s3-media4.fl.yelpcdn.com/bphoto/Wf58JBJMekfc-ejVkJ1Ksg/o.jpg"], "image_url": "https://s3-media4.fl.yelpcdn.com/bphoto/Wf58JBJMekfc-ejVkJ1Ksg/o.jpg", "review_count": 5, "categories": [{"title": "Venues & Event Spaces", "alias": "venues"}], "term": "attractions", "id": "rivington-hall-barn-preston", "url": "https://www.yelp.com/biz/rivington-hall-barn-preston?adjust_creative=92p07_JjKyriZTQxAXRiKQ&utm_campaign=yelp_api_v3&utm_medium=api_v3_business_lookup&utm_source=92p07_JjKyriZTQxAXRiKQ", "rating": 5.0, "price": "\u00a3\u00a3\u00a3\u00a3", "coordinates": {"longitude": -2.562, "latitude": 53.6246605}, "phone": "+441204669332", "name": "Rivington Hall Barn", "is_claimed": false}