{"location": {"zip_code": "77007", "address3": "", "city": "Houston", "address2": "", "state": "TX", "address1": "2400 Memorial Dr", "country": "US"}, "is_closed": false, "photos": ["https://s3-media2.fl.yelpcdn.com/bphoto/Q_hxO5C_QkwAbF09iy4e6Q/o.jpg", "https://s3-media4.fl.yelpcdn.com/bphoto/6Lntyl-jsSbd2T1RxFvVzw/o.jpg", "https://s3-media2.fl.yelpcdn.com/bphoto/HE8OVHb324CmuAqFaA9E-Q/o.jpg"], "image_url": "https://s3-media2.fl.yelpcdn.com/bphoto/Q_hxO5C_QkwAbF09iy4e6Q/o.jpg", "review_count": 21, "url": "https://www.yelp.com/biz/houston-police-officers-memorial-houston?adjust_creative=92p07_JjKyriZTQxAXRiKQ&utm_campaign=yelp_api_v3&utm_medium=api_v3_business_lookup&utm_source=92p07_JjKyriZTQxAXRiKQ", "term": "attractions", "id": "houston-police-officers-memorial-houston", "phone": "", "rating": 4.5, "categories": [{"title": "Local Flavor", "alias": "localflavor"}], "coordinates": {"longitude": -95.3830610926934, "latitude": 29.7628375254492}, "name": "Houston Police Officers Memorial", "is_claimed": false}