{"location": {"zip_code": "77505", "address3": "", "city": "Pasadena", "state": "TX", "address2": "", "address1": "5950 Fairmont Pkwy", "country": "US"}, "image_url": "https://s3-media4.fl.yelpcdn.com/bphoto/dsmbIVO_jALuHr00Dy7qZg/o.jpg", "is_closed": false, "photos": ["https://s3-media4.fl.yelpcdn.com/bphoto/dsmbIVO_jALuHr00Dy7qZg/o.jpg", "https://s3-media4.fl.yelpcdn.com/bphoto/J2n9oYV-N8aFTzpXWeK_6Q/o.jpg", "https://s3-media2.fl.yelpcdn.com/bphoto/21OpvaXZlEHDOxOE70q1FQ/o.jpg"], "url": "https://www.yelp.com/biz/itz-family-food-and-fun-pasadena?adjust_creative=92p07_JjKyriZTQxAXRiKQ&utm_campaign=yelp_api_v3&utm_medium=api_v3_business_lookup&utm_source=92p07_JjKyriZTQxAXRiKQ", "review_count": 34, "hours": [{"hours_type": "REGULAR", "is_open_now": true, "open": [{"start": "1100", "is_overnight": false, "end": "2300", "day": 0}, {"start": "1100", "is_overnight": false, "end": "2300", "day": 1}, {"start": "1100", "is_overnight": false, "end": "2300", "day": 2}, {"start": "1100", "is_overnight": false, "end": "2300", "day": 3}, {"start": "1100", "is_overnight": true, "end": "0100", "day": 4}, {"start": "1100", "is_overnight": true, "end": "0100", "day": 5}, {"start": "1100", "is_overnight": false, "end": "2300", "day": 6}]}], "term": "attractions", "price": "$$", "id": "itz-family-food-and-fun-pasadena", "phone": "+12819982424", "rating": 2.5, "categories": [{"alias": "arcades", "title": "Arcades"}, {"alias": "pizza", "title": "Pizza"}, {"alias": "bowling", "title": "Bowling"}], "coordinates": {"longitude": -95.1502609, "latitude": 29.6494846}, "name": "iT'Z Family Food and Fun", "is_claimed": true}