{"location": {"zip_code": "77021", "address3": "", "city": "Houston", "address2": "", "state": "TX", "address1": "5055 Griggs Rd", "country": "US"}, "image_url": "https://s3-media3.fl.yelpcdn.com/bphoto/mMN61YE2ObDppv-WNh29bA/o.jpg", "is_closed": false, "photos": ["https://s3-media2.fl.yelpcdn.com/bphoto/mMN61YE2ObDppv-WNh29bA/o.jpg", "https://s3-media2.fl.yelpcdn.com/bphoto/EKdoY298WjA3vtbGU8Kudg/o.jpg", "https://s3-media2.fl.yelpcdn.com/bphoto/RzLWBIZ42JtdzPVanvXhwA/o.jpg"], "url": "https://www.yelp.com/biz/louisiana-fish-house-houston?adjust_creative=92p07_JjKyriZTQxAXRiKQ&utm_campaign=yelp_api_v3&utm_medium=api_v3_business_lookup&utm_source=92p07_JjKyriZTQxAXRiKQ", "review_count": 25, "hours": [{"hours_type": "REGULAR", "is_open_now": false, "open": [{"end": "2100", "is_overnight": false, "start": "1100", "day": 0}, {"end": "2100", "is_overnight": false, "start": "1100", "day": 1}, {"end": "2100", "is_overnight": false, "start": "1100", "day": 2}, {"end": "2100", "is_overnight": false, "start": "1100", "day": 3}, {"end": "2130", "is_overnight": false, "start": "1100", "day": 4}, {"end": "2130", "is_overnight": false, "start": "1100", "day": 5}, {"end": "2000", "is_overnight": false, "start": "1100", "day": 6}]}], "term": "restaurants", "price": "$", "id": "louisiana-fish-house-houston", "phone": "+12815010432", "rating": 4.0, "categories": [{"alias": "cajun", "title": "Cajun/Creole"}], "coordinates": {"longitude": -95.3386699, "latitude": 29.698837}, "name": "Louisiana Fish House", "is_claimed": false}