{"location": {"zip_code": "77008", "address3": "", "city": "Houston", "address2": null, "state": "TX", "address1": "1221 W 11th St", "country": "US"}, "image_url": "https://s3-media1.fl.yelpcdn.com/bphoto/XocmzEyiXuaTJj4go5JMCA/o.jpg", "is_closed": false, "photos": ["https://s3-media3.fl.yelpcdn.com/bphoto/XocmzEyiXuaTJj4go5JMCA/o.jpg", "https://s3-media1.fl.yelpcdn.com/bphoto/axke2GJaqSjK3ppH7ER37A/o.jpg", "https://s3-media4.fl.yelpcdn.com/bphoto/elB_wfheonLPI7NJjidP1w/o.jpg"], "url": "https://www.yelp.com/biz/republic-diner-sojubang-houston-4?adjust_creative=92p07_JjKyriZTQxAXRiKQ&utm_campaign=yelp_api_v3&utm_medium=api_v3_business_lookup&utm_source=92p07_JjKyriZTQxAXRiKQ", "review_count": 198, "hours": [{"hours_type": "REGULAR", "is_open_now": true, "open": [{"end": "2200", "is_overnight": false, "start": "1100", "day": 0}, {"end": "2200", "is_overnight": false, "start": "1100", "day": 1}, {"end": "2200", "is_overnight": false, "start": "1100", "day": 2}, {"end": "2200", "is_overnight": false, "start": "1100", "day": 3}, {"end": "2300", "is_overnight": false, "start": "1100", "day": 4}, {"end": "2300", "is_overnight": false, "start": "1100", "day": 5}, {"end": "2200", "is_overnight": false, "start": "1100", "day": 6}]}], "term": "restaurants", "price": "$$", "id": "republic-diner-sojubang-houston-4", "phone": "+18326493601", "rating": 4.0, "categories": [{"alias": "korean", "title": "Korean"}, {"alias": "gastropubs", "title": "Gastropubs"}, {"alias": "cocktailbars", "title": "Cocktail Bars"}], "coordinates": {"longitude": -95.4091979996731, "latitude": 29.7902465650345}, "name": "Republic Diner + Sojubang", "is_claimed": true}