{"location": {"zip_code": "2912", "address3": null, "city": "Gungahlin", "address2": null, "state": "ACT", "address1": "Anthony Rolfe Ave", "country": "AU"}, "is_closed": false, "photos": [], "url": "https://www.yelp.com/biz/abode-the-apartment-hotel-gungahlin?adjust_creative=92p07_JjKyriZTQxAXRiKQ&utm_campaign=yelp_api_v3&utm_medium=api_v3_business_lookup&utm_source=92p07_JjKyriZTQxAXRiKQ", "review_count": 0, "image_url": "", "term": "hotels", "id": "abode-the-apartment-hotel-gungahlin", "phone": "+611300122633", "rating": 0.0, "categories": [], "coordinates": {"longitude": 149.1479492, "latitude": -35.1856613}, "name": "Abode The Apartment Hotel", "is_claimed": false}