{"location": {"zip_code": "2601", "address3": null, "city": "Canberra City", "address2": "Garema Arcade Bunda St", "state": "ACT", "address1": "Shop 8", "country": "AU"}, "image_url": "https://s3-media3.fl.yelpcdn.com/bphoto/85kARDK15QoLA-G_H4lxOw/o.jpg", "is_closed": false, "photos": ["https://s3-media3.fl.yelpcdn.com/bphoto/85kARDK15QoLA-G_H4lxOw/o.jpg", "https://s3-media2.fl.yelpcdn.com/bphoto/e8tPgWGEfV1PGHVLQMIwDg/o.jpg", "https://s3-media2.fl.yelpcdn.com/bphoto/OOa0RPPa4th5YYoBNVg6OQ/o.jpg"], "url": "https://www.yelp.com/biz/gus-cafe-canberra-city?adjust_creative=92p07_JjKyriZTQxAXRiKQ&utm_campaign=yelp_api_v3&utm_medium=api_v3_business_lookup&utm_source=92p07_JjKyriZTQxAXRiKQ", "review_count": 15, "hours": [{"hours_type": "REGULAR", "is_open_now": true, "open": [{"day": 0, "is_overnight": false, "start": "0730", "end": "2130"}, {"day": 1, "is_overnight": false, "start": "0730", "end": "2130"}, {"day": 2, "is_overnight": false, "start": "0730", "end": "2130"}, {"day": 3, "is_overnight": false, "start": "0730", "end": "2130"}, {"day": 4, "is_overnight": false, "start": "0730", "end": "2130"}, {"day": 5, "is_overnight": false, "start": "0730", "end": "2130"}, {"day": 6, "is_overnight": false, "start": "0730", "end": "2130"}]}], "term": "restaurants", "price": "$$", "id": "gus-cafe-canberra-city", "phone": "+61262488118", "rating": 4.0, "categories": [{"title": "Cafes", "alias": "cafes"}], "coordinates": {"longitude": 149.1330261, "latitude": -35.2786293}, "name": "Gus' Cafe", "is_claimed": false}