{"location": {"zip_code": "2616", "address3": null, "city": "Belconnen", "address2": null, "state": "ACT", "address1": "316 Emu Bank Way", "country": "AU"}, "is_closed": false, "photos": [], "url": "https://www.yelp.com/biz/student-flights-belconnen?adjust_creative=92p07_JjKyriZTQxAXRiKQ&utm_campaign=yelp_api_v3&utm_medium=api_v3_business_lookup&utm_source=92p07_JjKyriZTQxAXRiKQ", "review_count": 0, "image_url": "", "term": "hotels", "id": "student-flights-belconnen", "phone": "+61262094977", "rating": 0.0, "categories": [{"title": "Travel Services", "alias": "travelservices"}], "coordinates": {"longitude": 149.0703125, "latitude": -35.2366791}, "name": "Student Flights", "is_claimed": false}