{"location": {"zip_code": "7004", "address3": null, "city": "Battery Point", "state": "TAS", "address2": null, "address1": "15 Cromwell St", "country": "AU"}, "is_closed": false, "photos": [], "image_url": "", "review_count": 0, "url": "https://www.yelp.com/biz/battery-point-manor-battery-point?adjust_creative=92p07_JjKyriZTQxAXRiKQ&utm_campaign=yelp_api_v3&utm_medium=api_v3_business_lookup&utm_source=92p07_JjKyriZTQxAXRiKQ", "term": "hotels", "id": "battery-point-manor-battery-point", "phone": "+61362240888", "rating": 0.0, "categories": [{"title": "Bed & Breakfast", "alias": "bedbreakfast"}], "coordinates": {"longitude": 147.3343353, "latitude": -42.8919983}, "name": "Battery Point Manor", "is_claimed": false}