{"location": {"zip_code": "5033", "address3": null, "city": "Richmond", "address2": null, "state": "SA", "address1": "197 Richmond Rd", "country": "AU"}, "is_closed": false, "photos": [], "image_url": "", "review_count": 0, "url": "https://www.yelp.com/biz/classic-dynamics-sa-richmond?adjust_creative=92p07_JjKyriZTQxAXRiKQ&utm_campaign=yelp_api_v3&utm_medium=api_v3_business_lookup&utm_source=92p07_JjKyriZTQxAXRiKQ", "term": "hotels", "id": "classic-dynamics-sa-richmond", "phone": "+61884435181", "rating": 0.0, "categories": [{"title": "Hotels", "alias": "hotels"}], "coordinates": {"longitude": 138.5619659, "latitude": -34.9419899}, "name": "Classic Dynamics SA", "is_claimed": false}