{"location": {"zip_code": "5000", "address3": "", "city": "Adelaide", "address2": "", "state": "SA", "address1": "", "country": "AU"}, "is_closed": false, "photos": [], "image_url": "", "review_count": 0, "hours": [{"hours_type": "REGULAR", "is_open_now": true, "open": [{"day": 0, "is_overnight": false, "start": "0600", "end": "2130"}, {"day": 1, "is_overnight": false, "start": "0600", "end": "2130"}, {"day": 2, "is_overnight": false, "start": "0600", "end": "2130"}, {"day": 3, "is_overnight": false, "start": "0600", "end": "2130"}, {"day": 4, "is_overnight": false, "start": "0600", "end": "2130"}, {"day": 5, "is_overnight": false, "start": "0600", "end": "2130"}, {"day": 6, "is_overnight": false, "start": "0600", "end": "2130"}]}], "term": "hotels", "id": "dave-movers-adelaide", "url": "https://www.yelp.com/biz/dave-movers-adelaide?adjust_creative=92p07_JjKyriZTQxAXRiKQ&utm_campaign=yelp_api_v3&utm_medium=api_v3_business_lookup&utm_source=92p07_JjKyriZTQxAXRiKQ", "rating": 0.0, "categories": [{"title": "Transportation", "alias": "transport"}], "coordinates": {"longitude": 138.601209696134, "latitude": -34.9296814946921}, "phone": "+61449205039", "name": "Dave Movers", "is_claimed": false}