{"location": {"zip_code": "SW1P 1RL", "address3": "", "city": "London", "address2": "Artillery Row", "state": "XGL", "address1": "4 Westminster Palace Gardens", "country": "GB"}, "is_closed": false, "photos": [], "image_url": "", "review_count": 0, "url": "https://www.yelp.com/biz/association-of-leading-visitor-attractions-london?adjust_creative=92p07_JjKyriZTQxAXRiKQ&utm_campaign=yelp_api_v3&utm_medium=api_v3_business_lookup&utm_source=92p07_JjKyriZTQxAXRiKQ", "term": "attractions", "id": "association-of-leading-visitor-attractions-london", "phone": "+442072221728", "rating": 0.0, "categories": [{"title": "Social Clubs", "alias": "social_clubs"}], "coordinates": {"longitude": -0.13552, "latitude": 51.49726}, "name": "Association Of Leading Visitor Attractions", "is_claimed": false}