{"location": {"zip_code": "WC2A 1AA", "address3": "", "city": "London", "state": "XGL", "address2": "", "address1": "76 Chancery Lane", "country": "GB"}, "image_url": "https://s3-media1.fl.yelpcdn.com/bphoto/1lFKK25oSAeXzlDdChrAkQ/o.jpg", "is_closed": false, "photos": ["https://s3-media3.fl.yelpcdn.com/bphoto/1lFKK25oSAeXzlDdChrAkQ/o.jpg", "https://s3-media2.fl.yelpcdn.com/bphoto/dcIFhhkWH3xpqjwbFHY0Pg/o.jpg", "https://s3-media1.fl.yelpcdn.com/bphoto/-aaUgUOAIKShkfFCekQ22A/o.jpg"], "url": "https://www.yelp.com/biz/chilango-london-3?adjust_creative=92p07_JjKyriZTQxAXRiKQ&utm_campaign=yelp_api_v3&utm_medium=api_v3_business_lookup&utm_source=92p07_JjKyriZTQxAXRiKQ", "review_count": 31, "hours": [{"hours_type": "REGULAR", "is_open_now": false, "open": [{"start": "1130", "is_overnight": false, "end": "2100", "day": 0}, {"start": "1130", "is_overnight": false, "end": "2100", "day": 1}, {"start": "1130", "is_overnight": false, "end": "2100", "day": 2}, {"start": "1130", "is_overnight": false, "end": "2100", "day": 3}, {"start": "1130", "is_overnight": false, "end": "2100", "day": 4}]}], "term": "restaurants", "price": "\u00a3", "id": "chilango-london-3", "phone": "+442074301231", "rating": 4.0, "categories": [{"alias": "mexican", "title": "Mexican"}], "coordinates": {"longitude": -0.11380271719224, "latitude": 51.51788172845}, "name": "Chilango", "is_claimed": false}