{"location": {"zip_code": "E1 1PY", "address3": "", "city": "London", "state": "XGL", "address2": "", "address1": "2-10 Umberston Street", "country": "GB"}, "image_url": "https://s3-media1.fl.yelpcdn.com/bphoto/_o1S7PkGiuTGFzkjPszlQQ/o.jpg", "is_closed": false, "photos": ["https://s3-media1.fl.yelpcdn.com/bphoto/_o1S7PkGiuTGFzkjPszlQQ/o.jpg", "https://s3-media1.fl.yelpcdn.com/bphoto/SsIpSlNv5ZlMKR2bgY8CrQ/o.jpg", "https://s3-media1.fl.yelpcdn.com/bphoto/j8OQfQjpXkwzHZCdBwwnTQ/o.jpg"], "url": "https://www.yelp.com/biz/original-lahore-kebab-house-london-2?adjust_creative=92p07_JjKyriZTQxAXRiKQ&utm_campaign=yelp_api_v3&utm_medium=api_v3_business_lookup&utm_source=92p07_JjKyriZTQxAXRiKQ", "review_count": 116, "hours": [{"hours_type": "REGULAR", "is_open_now": false, "open": [{"start": "1130", "is_overnight": true, "end": "0100", "day": 0}, {"start": "1130", "is_overnight": true, "end": "0100", "day": 1}, {"start": "1130", "is_overnight": true, "end": "0100", "day": 2}, {"start": "1130", "is_overnight": true, "end": "0100", "day": 3}, {"start": "1130", "is_overnight": true, "end": "0100", "day": 4}, {"start": "1130", "is_overnight": true, "end": "0100", "day": 5}, {"start": "1130", "is_overnight": true, "end": "0100", "day": 6}]}], "term": "restaurants", "price": "\u00a3\u00a3", "id": "original-lahore-kebab-house-london-2", "phone": "+442074819738", "rating": 4.0, "categories": [{"alias": "indpak", "title": "Indian"}, {"alias": "pakistani", "title": "Pakistani"}, {"alias": "halal", "title": "Halal"}], "coordinates": {"longitude": -0.0630949, "latitude": 51.51461}, "name": "Original Lahore Kebab House", "is_claimed": true}