{"location": {"zip_code": "48226", "address3": "", "city": "Detroit", "address2": "", "state": "MI", "address1": "561 Monroe St", "country": "US"}, "image_url": "https://s3-media3.fl.yelpcdn.com/bphoto/ylw4Svj7RbcFpCMddLLE1Q/o.jpg", "is_closed": false, "photos": ["https://s3-media2.fl.yelpcdn.com/bphoto/ylw4Svj7RbcFpCMddLLE1Q/o.jpg", "https://s3-media3.fl.yelpcdn.com/bphoto/hE5dKLmTdkt-4_djN4G-4Q/o.jpg", "https://s3-media2.fl.yelpcdn.com/bphoto/2oIwEya0AfxJ2Xfc38mtlg/o.jpg"], "url": "https://www.yelp.com/biz/monroe-street-steakhouse-detroit?adjust_creative=92p07_JjKyriZTQxAXRiKQ&utm_campaign=yelp_api_v3&utm_medium=api_v3_business_lookup&utm_source=92p07_JjKyriZTQxAXRiKQ", "review_count": 20, "categories": [{"title": "Steakhouses", "alias": "steak"}], "term": "restaurants", "id": "monroe-street-steakhouse-detroit", "phone": "+13139613636", "rating": 3.5, "price": "$$$", "coordinates": {"longitude": -83.0414886, "latitude": 42.3355713}, "name": "Monroe Street Steakhouse", "is_claimed": false}