{"location": {"zip_code": "48209", "address3": null, "city": "Detroit", "address2": null, "state": "MI", "address1": "7208 W Fort St", "country": "US"}, "image_url": "https://s3-media4.fl.yelpcdn.com/bphoto/TyhdcXcpOYPGMwngLWA3Bw/o.jpg", "is_closed": false, "photos": ["https://s3-media1.fl.yelpcdn.com/bphoto/TyhdcXcpOYPGMwngLWA3Bw/o.jpg", "https://s3-media2.fl.yelpcdn.com/bphoto/ilovDb6ONRKDeWaUszELjg/o.jpg", "https://s3-media2.fl.yelpcdn.com/bphoto/nm6i75Jl74X_KkwhrUviDg/o.jpg"], "url": "https://www.yelp.com/biz/motzs-hamburgers-detroit?adjust_creative=92p07_JjKyriZTQxAXRiKQ&utm_campaign=yelp_api_v3&utm_medium=api_v3_business_lookup&utm_source=92p07_JjKyriZTQxAXRiKQ", "review_count": 51, "hours": [{"hours_type": "REGULAR", "is_open_now": false, "open": [{"day": 0, "is_overnight": false, "start": "1000", "end": "1600"}, {"day": 1, "is_overnight": false, "start": "1000", "end": "1600"}, {"day": 2, "is_overnight": false, "start": "1000", "end": "1600"}, {"day": 3, "is_overnight": false, "start": "1000", "end": "1600"}, {"day": 4, "is_overnight": false, "start": "1000", "end": "1600"}, {"day": 5, "is_overnight": false, "start": "1000", "end": "1600"}]}], "term": "restaurants", "price": "$", "id": "motzs-hamburgers-detroit", "phone": "", "rating": 4.5, "categories": [{"title": "Burgers", "alias": "burgers"}], "coordinates": {"longitude": -83.11348, "latitude": 42.30272}, "name": "Motz's Hamburgers", "is_claimed": false}