{"location": {"zip_code": "48218", "address3": "", "city": "Detroit", "address2": "", "state": "MI", "address1": "2054 Junction St", "country": "US"}, "image_url": "https://s3-media2.fl.yelpcdn.com/bphoto/hR3keQbXKvDauYt8w-_WjA/o.jpg", "is_closed": false, "photos": ["https://s3-media2.fl.yelpcdn.com/bphoto/hR3keQbXKvDauYt8w-_WjA/o.jpg", "https://s3-media3.fl.yelpcdn.com/bphoto/0lZ-o_1lA3lkj-DWJUgvFA/o.jpg", "https://s3-media2.fl.yelpcdn.com/bphoto/1p1AAV_P5FqHSB2TniySDA/o.jpg"], "url": "https://www.yelp.com/biz/pollo-chapin-detroit?adjust_creative=92p07_JjKyriZTQxAXRiKQ&utm_campaign=yelp_api_v3&utm_medium=api_v3_business_lookup&utm_source=92p07_JjKyriZTQxAXRiKQ", "review_count": 56, "hours": [{"hours_type": "REGULAR", "is_open_now": false, "open": [{"day": 0, "is_overnight": false, "start": "0930", "end": "2200"}, {"day": 1, "is_overnight": false, "start": "0930", "end": "2200"}, {"day": 2, "is_overnight": false, "start": "0930", "end": "2200"}, {"day": 3, "is_overnight": false, "start": "0930", "end": "2200"}, {"day": 4, "is_overnight": false, "start": "0930", "end": "2200"}, {"day": 5, "is_overnight": false, "start": "0930", "end": "2200"}, {"day": 6, "is_overnight": false, "start": "0930", "end": "2200"}]}], "term": "restaurants", "price": "$", "id": "pollo-chapin-detroit", "phone": "+13138431885", "rating": 4.0, "categories": [{"title": "Mexican", "alias": "mexican"}, {"title": "Latin American", "alias": "latin"}], "coordinates": {"longitude": -83.10257, "latitude": 42.31946}, "name": "Pollo Chapin", "is_claimed": false}