{"location": {"zip_code": "98105", "address3": "", "city": "Seattle", "state": "WA", "address2": null, "address1": "4725 University Way NE", "country": "US"}, "image_url": "https://s3-media3.fl.yelpcdn.com/bphoto/T4Camb2zzob1Ou1yFuM5kQ/o.jpg", "is_closed": false, "photos": ["https://s3-media2.fl.yelpcdn.com/bphoto/T4Camb2zzob1Ou1yFuM5kQ/o.jpg", "https://s3-media2.fl.yelpcdn.com/bphoto/KMvKWsBcIrv7R_RyIZuHPw/o.jpg", "https://s3-media2.fl.yelpcdn.com/bphoto/7M7qlDCn70CXrkEpHnjfbg/o.jpg"], "url": "https://www.yelp.com/biz/banh-mi-unwrapped-seattle?adjust_creative=92p07_JjKyriZTQxAXRiKQ&utm_campaign=yelp_api_v3&utm_medium=api_v3_business_lookup&utm_source=92p07_JjKyriZTQxAXRiKQ", "review_count": 178, "hours": [{"hours_type": "REGULAR", "is_open_now": false, "open": [{"start": "1030", "is_overnight": false, "end": "1930", "day": 0}, {"start": "1030", "is_overnight": false, "end": "1930", "day": 1}, {"start": "1030", "is_overnight": false, "end": "1930", "day": 2}, {"start": "1030", "is_overnight": false, "end": "1930", "day": 3}, {"start": "1030", "is_overnight": false, "end": "1830", "day": 4}, {"start": "1000", "is_overnight": false, "end": "1800", "day": 5}]}], "term": "restaurants", "price": "$", "id": "banh-mi-unwrapped-seattle", "phone": "+12064567192", "rating": 4.5, "categories": [{"alias": "vietnamese", "title": "Vietnamese"}, {"alias": "sandwiches", "title": "Sandwiches"}], "coordinates": {"longitude": -122.3133926, "latitude": 47.6638603}, "name": "Banh Mi Unwrapped", "is_claimed": true}